search.py
ers-1.0.2.dist-info/METADATA
ers-1.0.2.dist-info/WHEEL
ers-1.0.2.dist-info/entry_points.txt
ers-1.0.2.dist-info/top_level.txt
ers-1.0.2.dist-info/RECORD
